project_dilemma/__init__.py
project_dilemma/__main__.py
project_dilemma/config.py
project_dilemma/object_loaders.py
project_dilemma/interfaces/__init__.py
project_dilemma/interfaces/algorithm.py
project_dilemma/interfaces/base.py
project_dilemma/interfaces/generational_simulation.py
project_dilemma/interfaces/node.py
project_dilemma/interfaces/simulation.py
project_dilemma/simulations/__init__.py
project_dilemma/simulations/basic_simulation.py
project_dilemma/simulations/multiprocess_standard_simulation.py
project_dilemma/simulations/standard_generational_simulation.py
project_dilemma/simulations/standard_simulation.py
project_dilemma-1.1.0.dist-info/LICENSE
project_dilemma-1.1.0.dist-info/METADATA
project_dilemma-1.1.0.dist-info/WHEEL
project_dilemma-1.1.0.dist-info/entry_points.txt
project_dilemma-1.1.0.dist-info/top_level.txt
project_dilemma-1.1.0.dist-info/RECORD
