Metadata-Version: 2.1
Name: project_dilemma
Version: 1.1.0
Summary: The prisoner's dilemma in python
Author-email: Gabriele Ron <developer@groncyber.com>
Maintainer-email: Gabriele Ron <developer@groncyber.com>
License: 
Project-URL: Repository, https://github.com/Macr0Nerd/project_dilemma
Classifier: Development Status :: 4 - Beta
Classifier: Environment :: Console
Classifier: Intended Audience :: Developers
Classifier: License :: OSI Approved :: Apache Software License
Classifier: Natural Language :: English
Classifier: Operating System :: OS Independent
Classifier: Programming Language :: Python
Classifier: Programming Language :: Python :: 3
Classifier: Programming Language :: Python :: 3 :: Only
Classifier: Programming Language :: Python :: 3.11
Classifier: Programming Language :: Python :: 3.12
Classifier: Programming Language :: Python :: 3.13
Classifier: Topic :: Games/Entertainment :: Simulation
Requires-Python: >=3.11
License-File: LICENSE
Requires-Dist: platformdirs
Provides-Extra: tests
Requires-Dist: flake8 ; extra == 'tests'
Requires-Dist: pytest ; extra == 'tests'
